{
  "_class": "shapePath",
  "booleanOperation": -1,
  "clippingMaskMode": 0,
  "do_objectID": "DC88515F-612B-4543-A410-451677CE8BA3",
  "edited": true,
  "exportOptions": {
    "_class": "exportOptions",
    "exportFormats": [
    ],
    "includedLayerIds": [
    ],
    "layerOptions": 0,
    "shouldTrim": false
  },
  "frame": {
    "_class": "rect",
    "constrainProportions": false,
    "height": 125.2787991670407,
    "width": 497.6326604765288,
    "x": 0,
    "y": 1.287383159758677
  },
  "hasClippingMask": false,
  "isClosed": true,
  "isFixedToViewport": false,
  "isFlippedHorizontal": false,
  "isFlippedVertical": false,
  "isLocked": false,
  "isVisible": true,
  "layerListExpandedType": 0,
  "name": "Fill 74",
  "nameIsFixed": false,
  "pointRadiusBehaviour": 1,
  "points": [
    {
      "_class": "curvePoint",
      "cornerRadius": 0,
      "curveFrom": "{0.99554833333333337, 0.67447939380291422}",
      "curveMode": 4,
      "curveTo": "{1, 0.65724930684529925}",
      "hasCurveFrom": true,
      "hasCurveTo": false,
      "point": "{1, 0.65724930684529925}"
    },
    {
      "_class": "curvePoint",
      "cornerRadius": 0,
      "curveFrom": "{0.94686666666666663, 0.86504179871445319}",
      "curveMode": 3,
      "curveTo": "{0.99109666666666663, 0.69190279457715964}",
      "hasCurveFrom": true,
      "hasCurveTo": true,
      "point": "{0.98667000000000005, 0.70926131605678244}"
    },
    {
      "_class": "curvePoint",
      "cornerRadius": 0,
      "curveFrom": "{0.86498233333333341, 0.94158877383115469}",
      "curveMode": 3,
      "curveTo": "{0.90927733333333327, 1.0121880389183773}",
      "hasCurveFrom": true,
      "hasCurveTo": true,
      "point": "{0.88411499999999998, 0.97210190331230706}"
    },
    {
      "_class": "curvePoint",
      "cornerRadius": 0,
      "curveFrom": "{0.85232733333333333, 0.53099817171154517}",
      "curveMode": 3,
      "curveTo": "{0.85463833333333328, 0.80378382798563941}",
      "hasCurveFrom": true,
      "hasCurveTo": true,
      "point": "{0.85249800000000009, 0.55079959724379224}"
    },
    {
      "_class": "curvePoint",
      "cornerRadius": 0,
      "curveFrom": "{0.83852499999999996, 0.49500472793564382}",
      "curveMode": 3,
      "curveTo": "{0.85082966666666671, 0.51829904283961048}",
      "hasCurveFrom": true,
      "hasCurveTo": true,
      "point": "{0.84804666666666662, 0.51301071829425471}"
    },
    {
      "_class": "curvePoint",
      "cornerRadius": 0,
      "curveFrom": "{0.76214999999999999, 0.72665293921733509}",
      "curveMode": 2,
      "curveTo": "{0.81579566666666659, 0.56392639983334081}",
      "hasCurveFrom": true,
      "hasCurveTo": true,
      "point": "{0.78948566666666664, 0.64376897830341984}"
    },
    {
      "_class": "curvePoint",
      "cornerRadius": 0,
      "curveFrom": "{0.71084000000000003, 0.80953690013125046}",
      "curveMode": 3,
      "curveTo": "{0.73118499999999997, 0.82065509272197457}",
      "hasCurveFrom": true,
      "hasCurveTo": true,
      "point": "{0.71435566666666672, 0.81147665863374074}"
    },
    {
      "_class": "curvePoint",
      "cornerRadius": 0,
      "curveFrom": "{0.68584833333333339, 0.68650457245111673}",
      "curveMode": 3,
      "curveTo": "{0.70800733333333332, 0.80307147981202864}",
      "hasCurveFrom": true,
      "hasCurveTo": true,
      "point": "{0.70594066666666666, 0.7922114803325575}"
    },
    {
      "_class": "curvePoint",
      "cornerRadius": 0,
      "curveFrom": "{0.60266900000000001, 0.46576535113667267}",
      "curveMode": 2,
      "curveTo": "{0.66137666666666672, 0.57135971330295188}",
      "hasCurveFrom": true,
      "hasCurveTo": true,
      "point": "{0.63224266666666673, 0.51896107645820788}"
    },
    {
      "_class": "curvePoint",
      "cornerRadius": 0,
      "curveFrom": "{0.53114400000000006, 0.59970799285129095}",
      "curveMode": 3,
      "curveTo": "{0.57216833333333328, 0.4849841870845541}",
      "hasCurveFrom": true,
      "hasCurveTo": true,
      "point": "{0.53900566666666672, 0.57772847671385852}"
    },
    {
      "_class": "curvePoint",
      "cornerRadius": 0,
      "curveFrom": "{0.4552816666666667, 0.82534229074164389}",
      "curveMode": 3,
      "curveTo": "{0.52207000000000003, 0.62670307568321704}",
      "hasCurveFrom": true,
      "hasCurveTo": true,
      "point": "{0.512459, 0.65527644666187912}"
    },
    {
      "_class": "curvePoint",
      "cornerRadius": 0,
      "curveFrom": "{0.27668400000000004, 0.90473733448555105}",
      "curveMode": 3,
      "curveTo": "{0.36887166666666665, 1.0823013713295495}",
      "hasCurveFrom": true,
      "hasCurveTo": true,
      "point": "{0.30979400000000001, 0.9685136810995093}"
    },
    {
      "_class": "curvePoint",
      "cornerRadius": 0,
      "curveFrom": "{0.25448399999999993, 0.42277288794496004}",
      "curveMode": 3,
      "curveTo": "{0.26697166666666666, 0.69390610830703514}",
      "hasCurveFrom": true,
      "hasCurveTo": true,
      "point": "{0.25840233333333329, 0.50787201334670207}"
    },
    {
      "_class": "curvePoint",
      "cornerRadius": 0,
      "curveFrom": "{0.23128633333333332, 0.14232882677093142}",
      "curveMode": 3,
      "curveTo": "{0.25078166666666662, 0.34237949750420793}",
      "hasCurveFrom": true,
      "hasCurveTo": true,
      "point": "{0.24516566666666662, 0.28479184115689776}"
    },
    {
      "_class": "curvePoint",
      "cornerRadius": 0,
      "curveFrom": "{0.17175666666666667, -0.013156388892845093}",
      "curveMode": 2,
      "curveTo": "{0.2137733333333334, 0.055503117691887344}",
      "hasCurveFrom": true,
      "hasCurveTo": true,
      "point": "{0.19162566666666664, 0.019313711964881308}"
    },
    {
      "_class": "curvePoint",
      "cornerRadius": 0,
      "curveFrom": "{0.11417233333333328, 0.056877499484095484}",
      "curveMode": 3,
      "curveTo": "{0.14858399999999999, -0.0047512100711328926}",
      "hasCurveFrom": true,
      "hasCurveTo": true,
      "point": "{0.12078399999999996, 0.045029745845677267}"
    },
    {
      "_class": "curvePoint",
      "cornerRadius": 0,
      "curveFrom": "{0.066780666666666696, 0.1511709477809178}",
      "curveMode": 3,
      "curveTo": "{0.10731166666666665, 0.070518040161675705}",
      "hasCurveFrom": true,
      "hasCurveTo": true,
      "point": "{0.10005233333333338, 0.084967585921181588}"
    },
    {
      "_class": "curvePoint",
      "cornerRadius": 0,
      "curveFrom": "{0, 0.15838049388744313}",
      "curveMode": 4,
      "curveTo": "{0.02983833333333329, 0.22465005910903901}",
      "hasCurveFrom": false,
      "hasCurveTo": true,
      "point": "{0, 0.15838049388744313}"
    },
    {
      "_class": "curvePoint",
      "cornerRadius": 0,
      "curveFrom": "{0.010945666666666663, 0.18564568643575685}",
      "curveMode": 4,
      "curveTo": "{0, 0.16200181778117057}",
      "hasCurveFrom": true,
      "hasCurveTo": false,
      "point": "{0, 0.16200181778117057}"
    },
    {
      "_class": "curvePoint",
      "cornerRadius": 0,
      "curveFrom": "{0.05891900000000002, 0.17053543112489064}",
      "curveMode": 2,
      "curveTo": "{0.023612333333333329, 0.19272679802027434}",
      "hasCurveFrom": true,
      "hasCurveTo": true,
      "point": "{0.038248333333333294, 0.18353115105795675}"
    },
    {
      "_class": "curvePoint",
      "cornerRadius": 0,
      "curveFrom": "{0.10768233333333334, 0.0735236727901077}",
      "curveMode": 3,
      "curveTo": "{0.080973333333333355, 0.12666908355662942}",
      "hasCurveFrom": true,
      "hasCurveTo": true,
      "point": "{0.10042733333333338, 0.087959977877241802}"
    },
    {
      "_class": "curvePoint",
      "cornerRadius": 0,
      "curveFrom": "{0.14870566666666657, -0.0012927464475803176}",
      "curveMode": 3,
      "curveTo": "{0.1145306666666667, 0.059899020919373894}",
      "hasCurveFrom": true,
      "hasCurveTo": true,
      "point": "{0.12112999999999996, 0.048085693029122682}"
    },
    {
      "_class": "curvePoint",
      "cornerRadius": 0,
      "curveFrom": "{0.21323233333333338, 0.058217455528136619}",
      "curveMode": 2,
      "curveTo": "{0.17165899999999995, -0.009696601202055205}",
      "hasCurveFrom": true,
      "hasCurveTo": true,
      "point": "{0.19130833333333325, 0.022401436762019243}"
    },
    {
      "_class": "curvePoint",
      "cornerRadius": 0,
      "curveFrom": "{0.24996733333333335, 0.34329972423405825}",
      "curveMode": 3,
      "curveTo": "{0.23059499999999994, 0.14444733435044302}",
      "hasCurveFrom": true,
      "hasCurveTo": true,
      "point": "{0.24438499999999991, 0.28600336267893089}"
    },
    {
      "_class": "curvePoint",
      "cornerRadius": 0,
      "curveFrom": "{0.26618233333333335, 0.69526327722515979}",
      "curveMode": 3,
      "curveTo": "{0.25366566666666662, 0.42353422660634688}",
      "hasCurveFrom": true,
      "hasCurveTo": true,
      "point": "{0.2575763333333333, 0.50847049173791403}"
    },
    {
      "_class": "curvePoint",
      "cornerRadius": 0,
      "curveFrom": "{0.31968999999999997, 0.99130485045334227}",
      "curveMode": 3,
      "curveTo": "{0.27593566666666658, 0.90699751725944255}",
      "hasCurveFrom": true,
      "hasCurveTo": true,
      "point": "{0.30943133333333328, 0.97152196186241579}"
    },
    {
      "_class": "curvePoint",
      "cornerRadius": 0,
      "curveFrom": "{0.39795733333333333, 1}",
      "curveMode": 3,
      "curveTo": "{0.33075333333333334, 1}",
      "hasCurveFrom": true,
      "hasCurveTo": true,
      "point": "{0.34233000000000002, 1}"
    },
    {
      "_class": "curvePoint",
      "cornerRadius": 0,
      "curveFrom": "{0.52256666666666662, 0.62938431183853627}",
      "curveMode": 3,
      "curveTo": "{0.465499, 0.79912575944518838}",
      "hasCurveFrom": true,
      "hasCurveTo": true,
      "point": "{0.51296399999999998, 0.65796033095167283}"
    },
    {
      "_class": "curvePoint",
      "cornerRadius": 0,
      "curveFrom": "{0.60730833333333334, 0.39082049737697688}",
      "curveMode": 3,
      "curveTo": "{0.53163233333333326, 0.6024263028892517}",
      "hasCurveFrom": true,
      "hasCurveTo": true,
      "point": "{0.53949400000000003, 0.58044281455010771}"
    },
    {
      "_class": "curvePoint",
      "cornerRadius": 0,
      "curveFrom": "{0.70747933333333335, 0.80581891932920768}",
      "curveMode": 3,
      "curveTo": "{0.65480899999999997, 0.5287552018117373}",
      "hasCurveFrom": true,
      "hasCurveTo": true,
      "point": "{0.70527300000000004, 0.79421346999519593}"
    },
    {
      "_class": "curvePoint",
      "cornerRadius": 0,
      "curveFrom": "{0.715063, 0.81522774111671337}",
      "curveMode": 2,
      "curveTo": "{0.71049800000000007, 0.8127384947107873}",
      "hasCurveFrom": true,
      "hasCurveTo": true,
      "point": "{0.71424166666666666, 0.81477358605435557}"
    },
    {
      "_class": "curvePoint",
      "cornerRadius": 0,
      "curveFrom": "{0.73426066666666667, 0.81545150847979919}",
      "curveMode": 3,
      "curveTo": "{0.71591833333333332, 0.81545150847979919}",
      "hasCurveFrom": true,
      "hasCurveTo": true,
      "point": "{0.71680500000000003, 0.81545150847979919}"
    },
    {
      "_class": "curvePoint",
      "cornerRadius": 0,
      "curveFrom": "{0.81500666666666666, 0.57055203228826312}",
      "curveMode": 2,
      "curveTo": "{0.76257333333333344, 0.72959634068561896}",
      "hasCurveFrom": true,
      "hasCurveTo": true,
      "point": "{0.78999000000000008, 0.64642108497952078}"
    },
    {
      "_class": "curvePoint",
      "cornerRadius": 0,
      "curveFrom": "{0.85020299999999993, 0.52080020585067133}",
      "curveMode": 3,
      "curveTo": "{0.83863100000000002, 0.49891734662155418}",
      "hasCurveFrom": true,
      "hasCurveTo": true,
      "point": "{0.84768900000000003, 0.51603488786400753}"
    },
    {
      "_class": "curvePoint",
      "cornerRadius": 0,
      "curveFrom": "{0.85381666666666656, 0.80536608833408707}",
      "curveMode": 3,
      "curveTo": "{0.85150599999999999, 0.53221366543528992}",
      "hasCurveFrom": true,
      "hasCurveTo": true,
      "point": "{0.85165966666666659, 0.55092935583303726}"
    },
    {
      "_class": "curvePoint",
      "cornerRadius": 0,
      "curveFrom": "{0.90948066666666671, 1.0161311111507434}",
      "curveMode": 3,
      "curveTo": "{0.86433066666666669, 0.94414157546446598}",
      "hasCurveFrom": true,
      "hasCurveTo": true,
      "point": "{0.88380499999999995, 0.97520816505076591}"
    },
    {
      "_class": "curvePoint",
      "cornerRadius": 0,
      "curveFrom": "{0.99149566666666666, 0.69503818579483667}",
      "curveMode": 3,
      "curveTo": "{0.94725733333333328, 0.868208967545823}",
      "hasCurveFrom": true,
      "hasCurveTo": true,
      "point": "{0.98725600000000002, 0.71162080387346338}"
    },
    {
      "_class": "curvePoint",
      "cornerRadius": 0,
      "curveFrom": "{1, 0.66190340318403873}",
      "curveMode": 4,
      "curveTo": "{0.99574399999999996, 0.67842379010251719}",
      "hasCurveFrom": false,
      "hasCurveTo": true,
      "point": "{1, 0.66190340318403873}"
    }
  ],
  "resizingConstraint": 63,
  "resizingType": 0,
  "rotation": 0,
  "shouldBreakMaskChain": false,
  "style": {
    "_class": "style",
    "blur": {
      "_class": "blur",
      "center": "{0.5, 0.5}",
      "isEnabled": false,
      "motionAngle": 0,
      "radius": 1.658775534921763,
      "saturation": 1,
      "type": 0
    },
    "borderOptions": {
      "_class": "borderOptions",
      "dashPattern": [
      ],
      "isEnabled": true,
      "lineCapStyle": 0,
      "lineJoinStyle": 0
    },
    "borders": [
    ],
    "colorControls": {
      "_class": "colorControls",
      "brightness": 0,
      "contrast": 1,
      "hue": 0,
      "isEnabled": false,
      "saturation": 1
    },
    "contextSettings": {
      "_class": "graphicsContextSettings",
      "blendMode": 0,
      "opacity": 1
    },
    "do_objectID": "C9362DFD-1879-4657-A091-9CD6858F774F",
    "endMarkerType": 0,
    "fills": [
      {
        "_class": "fill",
        "color": {
          "_class": "color",
          "alpha": 1,
          "blue": 0.482,
          "green": 0.165,
          "red": 0.933
        },
        "contextSettings": {
          "_class": "graphicsContextSettings",
          "blendMode": 0,
          "opacity": 1
        },
        "fillType": 0,
        "gradient": {
          "_class": "gradient",
          "elipseLength": 0,
          "from": "{0.5, 0}",
          "gradientType": 0,
          "stops": [
            {
              "_class": "gradientStop",
              "color": {
                "_class": "color",
                "alpha": 1,
                "blue": 1,
                "green": 1,
                "red": 1
              },
              "position": 0
            },
            {
              "_class": "gradientStop",
              "color": {
                "_class": "color",
                "alpha": 1,
                "blue": 0,
                "green": 0,
                "red": 0
              },
              "position": 1
            }
          ],
          "to": "{0.5, 1}"
        },
        "isEnabled": true,
        "noiseIndex": 0,
        "noiseIntensity": 0,
        "patternFillType": 1,
        "patternTileScale": 1
      }
    ],
    "innerShadows": [
    ],
    "miterLimit": 10,
    "shadows": [
    ],
    "startMarkerType": 0,
    "windingRule": 1
  }
}