{
  "_class": "group",
  "booleanOperation": 0,
  "clippingMaskMode": 0,
  "do_objectID": "632D3CF1-317D-4AA0-A2EF-9369B708D549",
  "exportOptions": {
    "_class": "exportOptions",
    "exportFormats": [
      {
        "_class": "exportFormat",
        "absoluteSize": 0,
        "fileFormat": "svg",
        "name": "",
        "namingScheme": 0,
        "scale": 1,
        "visibleScaleType": 0
      }
    ],
    "includedLayerIds": [
    ],
    "layerOptions": 0,
    "shouldTrim": false
  },
  "frame": {
    "_class": "rect",
    "constrainProportions": true,
    "height": 35,
    "width": 60,
    "x": 150,
    "y": 42
  },
  "groupLayout": {
    "_class": "MSImmutableFreeformGroupLayout"
  },
  "hasClickThrough": false,
  "hasClippingMask": false,
  "isFixedToViewport": false,
  "isFlippedHorizontal": false,
  "isFlippedVertical": false,
  "isLocked": false,
  "isVisible": true,
  "layerListExpandedType": 0,
  "layers": [
    {
      "class": "shapeGroup",
      "id": "E61E3296-7174-4471-BAE2-D80247247093"
    },
    {
      "class": "shapePath",
      "id": "3BD6F56D-FB13-4075-8A2F-553938AA7D15"
    },
    {
      "class": "shapePath",
      "id": "43589EE7-11F6-405D-BBD1-6E91C2BC9861"
    },
    {
      "class": "shapePath",
      "id": "E140F32A-2DEC-41B1-8DA6-48C4C4AA1495"
    },
    {
      "class": "shapeGroup",
      "id": "4A4A47E4-5E66-43DA-9C5B-6D56F3E74BBB"
    },
    {
      "class": "shapePath",
      "id": "0FE08D6B-0EC4-449A-ACCD-3963B3D60337"
    }
  ],
  "name": "Logo Copy 2",
  "nameIsFixed": true,
  "resizingConstraint": 63,
  "resizingType": 0,
  "rotation": 0,
  "shouldBreakMaskChain": false,
  "style": {
    "_class": "style",
    "blur": {
      "_class": "blur",
      "center": "{0.5, 0.5}",
      "isEnabled": false,
      "motionAngle": 0,
      "radius": 10,
      "saturation": 1,
      "type": 0
    },
    "borderOptions": {
      "_class": "borderOptions",
      "dashPattern": [
      ],
      "isEnabled": true,
      "lineCapStyle": 0,
      "lineJoinStyle": 0
    },
    "borders": [
    ],
    "colorControls": {
      "_class": "colorControls",
      "brightness": 0,
      "contrast": 1,
      "hue": 0,
      "isEnabled": false,
      "saturation": 1
    },
    "contextSettings": {
      "_class": "graphicsContextSettings",
      "blendMode": 0,
      "opacity": 1
    },
    "do_objectID": "C0D801C5-CC4A-4F0B-9F2A-F78C6BDD97C3",
    "endMarkerType": 0,
    "fills": [
    ],
    "innerShadows": [
    ],
    "miterLimit": 10,
    "shadows": [
    ],
    "startMarkerType": 0,
    "windingRule": 1
  }
}