{
  "_class": "shapePath",
  "booleanOperation": -1,
  "clippingMaskMode": 0,
  "do_objectID": "70762EA3-07FB-4919-B7A4-798D6F6A2F46",
  "edited": true,
  "exportOptions": {
    "_class": "exportOptions",
    "exportFormats": [
    ],
    "includedLayerIds": [
    ],
    "layerOptions": 0,
    "shouldTrim": false
  },
  "frame": {
    "_class": "rect",
    "constrainProportions": false,
    "height": 8.08789226744186,
    "width": 11.18362476710725,
    "x": 13.58340685237768,
    "y": 117.3088511571407
  },
  "hasClippingMask": false,
  "isClosed": false,
  "isFixedToViewport": false,
  "isFlippedHorizontal": false,
  "isFlippedVertical": false,
  "isLocked": false,
  "isVisible": true,
  "layerListExpandedType": 0,
  "name": "Fill 246",
  "nameIsFixed": false,
  "pointRadiusBehaviour": 1,
  "points": [
    {
      "_class": "curvePoint",
      "cornerRadius": 0,
      "curveFrom": "{0.4680803519104369, 0.95815096274616818}",
      "curveMode": 4,
      "curveTo": "{0.4680803519104369, 0.95815096274616818}",
      "hasCurveFrom": true,
      "hasCurveTo": false,
      "point": "{0.4680803519104369, 0.95815096274616818}"
    },
    {
      "_class": "curvePoint",
      "cornerRadius": 0,
      "curveFrom": "{0.58071498536353106, 0.84828789022749274}",
      "curveMode": 2,
      "curveTo": "{0.4893196818297435, 0.9305291982053121}",
      "hasCurveFrom": true,
      "hasCurveTo": true,
      "point": "{0.53504741763335018, 0.88909655139402821}"
    },
    {
      "_class": "curvePoint",
      "cornerRadius": 0,
      "curveFrom": "{0.80117080639565552, 0.73958959091234699}",
      "curveMode": 3,
      "curveTo": "{0.65213448851995348, 0.79370994583351218}",
      "hasCurveFrom": true,
      "hasCurveTo": true,
      "point": "{0.7515622298560849, 0.75747717939512993}"
    },
    {
      "_class": "curvePoint",
      "cornerRadius": 0,
      "curveFrom": "{0.93495451765791782, 0.72290837467607649}",
      "curveMode": 4,
      "curveTo": "{0.85757837523234126, 0.7261115009857847}",
      "hasCurveFrom": true,
      "hasCurveTo": true,
      "point": "{0.91964174297105217, 0.72374035553574134}"
    },
    {
      "_class": "curvePoint",
      "cornerRadius": 0,
      "curveFrom": "{0.98489401860133019, 0.73522169139910898}",
      "curveMode": 4,
      "curveTo": "{0.95141048573987352, 0.72186839860149643}",
      "hasCurveFrom": true,
      "hasCurveTo": true,
      "point": "{0.96804695804210661, 0.72902343399460967}"
    },
    {
      "_class": "curvePoint",
      "cornerRadius": 0,
      "curveFrom": "{1.0009588942060179, 0.8099751716399497}",
      "curveMode": 4,
      "curveTo": "{0.99960511255393791, 0.75872515068462643}",
      "hasCurveFrom": true,
      "hasCurveTo": true,
      "point": "{0.99990595292106665, 0.78468295350615358}"
    },
    {
      "_class": "curvePoint",
      "cornerRadius": 0,
      "curveFrom": "{0.9662118318026196, 0.8708761705673792}",
      "curveMode": 4,
      "curveTo": "{0.99310696062395154, 0.83564178116059473}",
      "hasCurveFrom": true,
      "hasCurveTo": true,
      "point": "{0.97953906006643421, 0.8531133792135458}"
    },
    {
      "_class": "curvePoint",
      "cornerRadius": 0,
      "curveFrom": "{0.7986437473117719, 0.96147888618482547}",
      "curveMode": 4,
      "curveTo": "{0.94936477124339647, 0.88189991695793168}",
      "hasCurveFrom": true,
      "hasCurveTo": true,
      "point": "{0.93257787875759857, 0.89096850832827312}"
    },
    {
      "_class": "curvePoint",
      "cornerRadius": 0,
      "curveFrom": "{0.45640774566583209, 0.95473984122154465}",
      "curveMode": 4,
      "curveTo": "{0.63236927639957863, 0.99617248803282854}",
      "hasCurveFrom": false,
      "hasCurveTo": true,
      "point": "{0.45640774566583209, 0.95473984122154465}"
    },
    {
      "_class": "curvePoint",
      "cornerRadius": 0,
      "curveFrom": "{0.45045110639667807, 0.95336707280309851}",
      "curveMode": 1,
      "curveTo": "{0.45045110639667807, 0.95336707280309851}",
      "hasCurveFrom": false,
      "hasCurveTo": false,
      "point": "{0.45045110639667807, 0.95336707280309851}"
    },
    {
      "_class": "curvePoint",
      "cornerRadius": 0,
      "curveFrom": "{0.46001783007137992, 0.80914319078028552}",
      "curveMode": 4,
      "curveTo": "{0.4510227030942231, 0.94500566516347217}",
      "hasCurveFrom": true,
      "hasCurveTo": false,
      "point": "{0.4510227030942231, 0.94500566516347217}"
    },
    {
      "_class": "curvePoint",
      "cornerRadius": 0,
      "curveFrom": "{0.53980069543398823, 0.45829686225983418}",
      "curveMode": 3,
      "curveTo": "{0.48228001723892527, 0.66778964272331465}",
      "hasCurveFrom": true,
      "hasCurveTo": true,
      "point": "{0.52051682790102005, 0.52814165542865543}"
    },
    {
      "_class": "curvePoint",
      "cornerRadius": 0,
      "curveFrom": "{0.6046618785869986, 0.28765758794267826}",
      "curveMode": 4,
      "curveTo": "{0.56242389104208823, 0.38907605473576118}",
      "hasCurveFrom": true,
      "hasCurveTo": true,
      "point": "{0.59025162500152006, 0.32114481754416813}"
    },
    {
      "_class": "curvePoint",
      "cornerRadius": 0,
      "curveFrom": "{0.67229079311759565, 0.20820341584473409}",
      "curveMode": 4,
      "curveTo": "{0.62235129217418339, 0.25425355642715519}",
      "hasCurveFrom": true,
      "hasCurveTo": true,
      "point": "{0.647441378792741, 0.23083329522760399}"
    },
    {
      "_class": "curvePoint",
      "cornerRadius": 0,
      "curveFrom": "{0.76654408013910835, 0.22084952491163212}",
      "curveMode": 2,
      "curveTo": "{0.70439046029025898, 0.19576530199275197}",
      "hasCurveFrom": true,
      "hasCurveTo": true,
      "point": "{0.73525668195769356, 0.20824501488771693}"
    },
    {
      "_class": "curvePoint",
      "cornerRadius": 0,
      "curveFrom": "{0.8030360166718552, 0.34452347970073594}",
      "curveMode": 4,
      "curveTo": "{0.78787366216855392, 0.26099260139043601}",
      "hasCurveFrom": true,
      "hasCurveTo": true,
      "point": "{0.79500357886951123, 0.30230045107277076}"
    },
    {
      "_class": "curvePoint",
      "cornerRadius": 0,
      "curveFrom": "{0.76185097041189631, 0.50592776647561732}",
      "curveMode": 4,
      "curveTo": "{0.79701920932927528, 0.38920085186471082}",
      "hasCurveFrom": true,
      "hasCurveTo": true,
      "point": "{0.78588811574550255, 0.42813755609700155}"
    },
    {
      "_class": "curvePoint",
      "cornerRadius": 0,
      "curveFrom": "{0.61663532519873254, 0.77740312098409081}",
      "curveMode": 4,
      "curveTo": "{0.72728441222877527, 0.57423339505405935}",
      "hasCurveFrom": true,
      "hasCurveTo": true,
      "point": "{0.69094289587959323, 0.64266382076145157}"
    },
    {
      "_class": "curvePoint",
      "cornerRadius": 0,
      "curveFrom": "{0.41320706894610904, 0.98860146220988299}",
      "curveMode": 4,
      "curveTo": "{0.52253245836078432, 0.89675077530294012}",
      "hasCurveFrom": false,
      "hasCurveTo": true,
      "point": "{0.41320706894610904, 0.98860146220988299}"
    },
    {
      "_class": "curvePoint",
      "cornerRadius": 0,
      "curveFrom": "{0.41037916949509645, 0.99097260765992634}",
      "curveMode": 1,
      "curveTo": "{0.41037916949509645, 0.99097260765992634}",
      "hasCurveFrom": false,
      "hasCurveTo": false,
      "point": "{0.41037916949509645, 0.99097260765992634}"
    },
    {
      "_class": "curvePoint",
      "cornerRadius": 0,
      "curveFrom": "{0.39675110086415311, 0.98606392058790704}",
      "curveMode": 4,
      "curveTo": "{0.40740084986051933, 0.98993263158534628}",
      "hasCurveFrom": true,
      "hasCurveTo": false,
      "point": "{0.40740084986051933, 0.98993263158534628}"
    },
    {
      "_class": "curvePoint",
      "cornerRadius": 0,
      "curveFrom": "{0.36326756800269644, 0.97283542491924413}",
      "curveMode": 4,
      "curveTo": "{0.38568017535380617, 0.98202881341853465}",
      "hasCurveFrom": true,
      "hasCurveTo": true,
      "point": "{0.37433849351304338, 0.97795210720617942}"
    },
    {
      "_class": "curvePoint",
      "cornerRadius": 0,
      "curveFrom": "{0.24527797601470636, 0.91355678866816015}",
      "curveMode": 4,
      "curveTo": "{0.35195597019864644, 0.96763554454634204}",
      "hasCurveFrom": true,
      "hasCurveTo": true,
      "point": "{0.34064437239459627, 0.96243566417343984}"
    },
    {
      "_class": "curvePoint",
      "cornerRadius": 0,
      "curveFrom": "{0.066127537389392199, 0.67390470204184716}",
      "curveMode": 3,
      "curveTo": "{0.1614638497325695, 0.82990111322891058}",
      "hasCurveFrom": true,
      "hasCurveTo": true,
      "point": "{0.097926364194926591, 0.72590350577086826}"
    },
    {
      "_class": "curvePoint",
      "cornerRadius": 0,
      "curveFrom": "{0.0095093802957162046, 0.5261033023224776}",
      "curveMode": 3,
      "curveTo": "{0.039743837192179853, 0.61637322559605834}",
      "hasCurveFrom": true,
      "hasCurveTo": true,
      "point": "{0.019256608190695447, 0.55580501901249435}"
    },
    {
      "_class": "curvePoint",
      "cornerRadius": 0,
      "curveFrom": "{0.001446858456659232, 0.43778853406910784}",
      "curveMode": 4,
      "curveTo": "{-0.0024941503527305536, 0.49382244496750138}",
      "hasCurveFrom": true,
      "hasCurveTo": true,
      "point": "{0.00045408524513352482, 0.45617531106769005}"
    },
    {
      "_class": "curvePoint",
      "cornerRadius": 0,
      "curveFrom": "{0.038720979943941317, 0.40222135231845785}",
      "curveMode": 4,
      "curveTo": "{0.010441985433816039, 0.41678101736258349}",
      "hasCurveFrom": true,
      "hasCurveTo": true,
      "point": "{0.02458148268887857, 0.40979237814140279}"
    },
    {
      "_class": "curvePoint",
      "cornerRadius": 0,
      "curveFrom": "{0.24037427803050371, 0.51720110712406919}",
      "curveMode": 4,
      "curveTo": "{0.052770225088865148, 0.40692204417556133}",
      "hasCurveFrom": true,
      "hasCurveTo": true,
      "point": "{0.064262327113192533, 0.41249631593531239}"
    },
    {
      "_class": "curvePoint",
      "cornerRadius": 0,
      "curveFrom": "{0.39831547077322382, 0.96555559239718125}",
      "curveMode": 4,
      "curveTo": "{0.36034941644154517, 0.73759283684915244}",
      "hasCurveFrom": false,
      "hasCurveTo": true,
      "point": "{0.39831547077322382, 0.96555559239718125}"
    },
    {
      "_class": "curvePoint",
      "cornerRadius": 0,
      "curveFrom": "{0.30096352797028253, 0.6860516225929465}",
      "curveMode": 4,
      "curveTo": "{0.38486790636255808, 0.97146265650079788}",
      "hasCurveFrom": true,
      "hasCurveTo": false,
      "point": "{0.38486790636255808, 0.97146265650079788}"
    },
    {
      "_class": "curvePoint",
      "cornerRadius": 0,
      "curveFrom": "{0.26979646593571904, 0.11681031841060643}",
      "curveMode": 3,
      "curveTo": "{0.2688638607976192, 0.40059898964211232}",
      "hasCurveFrom": true,
      "hasCurveTo": true,
      "point": "{0.26952570960530292, 0.14888318055066671}"
    },
    {
      "_class": "curvePoint",
      "cornerRadius": 0,
      "curveFrom": "{0.28625243401767475, 0.040268079321487182}",
      "curveMode": 3,
      "curveTo": "{0.27244386116645419, 0.08469585722756276}",
      "hasCurveFrom": true,
      "hasCurveTo": true,
      "point": "{0.28158940832717555, 0.054994140537545935}"
    },
    {
      "_class": "curvePoint",
      "cornerRadius": 0,
      "curveFrom": "{0.31179378118692619, 0.0052416851296186}",
      "curveMode": 2,
      "curveTo": "{0.29287092209451271, 0.026207602793160124}",
      "hasCurveFrom": true,
      "hasCurveTo": true,
      "point": "{0.30231730962236303, 0.015766243004372484}"
    },
    {
      "_class": "curvePoint",
      "cornerRadius": 0,
      "curveFrom": "{0.36049983662510976, -8.2992372233168843e-05}",
      "curveMode": 4,
      "curveTo": "{0.3238574799087986, 0.00020820092864955761}",
      "hasCurveFrom": true,
      "hasCurveTo": true,
      "point": "{0.33562033826354226, 2.0571373307107816e-07}"
    },
    {
      "_class": "curvePoint",
      "cornerRadius": 0,
      "curveFrom": "{0.40162471481164275, 0.074296096481758528}",
      "curveMode": 4,
      "curveTo": "{0.37924219149724581, 0.025084428632613228}",
      "hasCurveFrom": true,
      "hasCurveTo": true,
      "point": "{0.39010252875060253, 0.049336670691828621}"
    },
    {
      "_class": "curvePoint",
      "cornerRadius": 0,
      "curveFrom": "{0.42882068400010359, 0.23649076507332129}",
      "curveMode": 4,
      "curveTo": "{0.40866437940246114, 0.10146027154979941}",
      "hasCurveFrom": true,
      "hasCurveTo": true,
      "point": "{0.41335748912967341, 0.12858284757485688}"
    },
    {
      "_class": "curvePoint",
      "cornerRadius": 0,
      "curveFrom": "{0.45054135850681676, 0.60946778446084449}",
      "curveMode": 3,
      "curveTo": "{0.43754505464684429, 0.33641166631900837}",
      "hasCurveFrom": true,
      "hasCurveTo": true,
      "point": "{0.44181698786007606, 0.42743037236628706}"
    },
    {
      "_class": "curvePoint",
      "cornerRadius": 0,
      "curveFrom": "{0.43014438161547108, 0.89978750544071517}",
      "curveMode": 3,
      "curveTo": "{0.44250892070447262, 0.75360846839769058}",
      "hasCurveFrom": true,
      "hasCurveTo": true,
      "point": "{0.43435614675527695, 0.85107502610736796}"
    },
    {
      "_class": "curvePoint",
      "cornerRadius": 0,
      "curveFrom": "{0.42102891849146273, 0.97400019812277383}",
      "curveMode": 3,
      "curveTo": "{0.42590253243895232, 0.93710184699666044}",
      "hasCurveFrom": true,
      "hasCurveTo": true,
      "point": "{0.42265345647395935, 0.96214447087255717}"
    },
    {
      "_class": "curvePoint",
      "cornerRadius": 0,
      "curveFrom": "{0.4178400105998954, 0.99683807272056024}",
      "curveMode": 4,
      "curveTo": "{0.41973530491280808, 0.98323518566504831}",
      "hasCurveFrom": true,
      "hasCurveTo": true,
      "point": "{0.41877261573799518, 0.99047341914412779}"
    },
    {
      "_class": "curvePoint",
      "cornerRadius": 0,
      "curveFrom": "{0.41687732142508271, 0.99995800094430154}",
      "curveMode": 4,
      "curveTo": "{0.41726841390235031, 1.0000411990302678}",
      "hasCurveFrom": true,
      "hasCurveTo": true,
      "point": "{0.41708790968207293, 0.99999959998728438}"
    },
    {
      "_class": "curvePoint",
      "cornerRadius": 0,
      "curveFrom": "{0.41832135518730168, 0.98298559140714903}",
      "curveMode": 2,
      "curveTo": "{0.41705782564536009, 0.99667167654862709}",
      "hasCurveFrom": true,
      "hasCurveTo": true,
      "point": "{0.41762942234290512, 0.99022382488622851}"
    },
    {
      "_class": "curvePoint",
      "cornerRadius": 0,
      "curveFrom": "{0.42286404473094957, 0.93647786135191213}",
      "curveMode": 3,
      "curveTo": "{0.41922387628868873, 0.97358420769294207}",
      "hasCurveFrom": true,
      "hasCurveTo": true,
      "point": "{0.42036706968377896, 0.9616452823567585}"
    },
    {
      "_class": "curvePoint",
      "cornerRadius": 0,
      "curveFrom": "{0.43661244950874445, 0.75298448275294294}",
      "curveMode": 3,
      "curveTo": "{0.42641396106307172, 0.89912192075298347}",
      "hasCurveFrom": true,
      "hasCurveTo": true,
      "point": "{0.42987362528505496, 0.85036784237665342}"
    },
    {
      "_class": "curvePoint",
      "cornerRadius": 0,
      "curveFrom": "{0.42854992766968747, 0.33795083090938766}",
      "curveMode": 3,
      "curveTo": "{0.44326102162229503, 0.60930138828891134}",
      "hasCurveFrom": true,
      "hasCurveTo": true,
      "point": "{0.43336337354375126, 0.42830395226893464}"
    },
    {
      "_class": "curvePoint",
      "cornerRadius": 0,
      "curveFrom": "{0.39885698343405607, 0.10603616627795324}",
      "curveMode": 4,
      "curveTo": "{0.41916370821526305, 0.23798833062071717}",
      "hasCurveFrom": true,
      "hasCurveTo": true,
      "point": "{0.40342975701441675, 0.13186917197053075}"
    },
    {
      "_class": "curvePoint",
      "cornerRadius": 0,
      "curveFrom": "{0.37087882929105992, 0.034735406604719521}",
      "curveMode": 4,
      "curveTo": "{0.39190757095337653, 0.080161561542392332}",
      "hasCurveFrom": true,
      "hasCurveTo": true,
      "point": "{0.3811976538835844, 0.057365285987589394}"
    },
    {
      "_class": "curvePoint",
      "cornerRadius": 0,
      "curveFrom": "{0.31606571440015774, 0.014726266929791823}",
      "curveMode": 4,
      "curveTo": "{0.35475378561294596, 0.014767865972775239}",
      "hasCurveFrom": true,
      "hasCurveTo": true,
      "point": "{0.3356504223002551, 0.015225455445590445}"
    },
    {
      "_class": "curvePoint",
      "cornerRadius": 0,
      "curveFrom": "{0.28396604722749441, 0.0877325873653379}",
      "curveMode": 4,
      "curveTo": "{0.29960974631820203, 0.03456901043278645}",
      "hasCurveFrom": true,
      "hasCurveTo": true,
      "point": "{0.2920586531032644, 0.06123399698502871}"
    },
    {
      "_class": "curvePoint",
      "cornerRadius": 0,
      "curveFrom": "{0.28158940832717555, 0.39872703270786747}",
      "curveMode": 3,
      "curveTo": "{0.28137882007018511, 0.11834948300098572}",
      "hasCurveFrom": true,
      "hasCurveTo": true,
      "point": "{0.28128856796004642, 0.14888318055066671}"
    },
    {
      "_class": "curvePoint",
      "cornerRadius": 0,
      "curveFrom": "{0.39798454636938208, 0.96401642780680197}",
      "curveMode": 4,
      "curveTo": "{0.31426067219738391, 0.68155892595075895}",
      "hasCurveFrom": false,
      "hasCurveTo": true,
      "point": "{0.39798454636938208, 0.96401642780680197}"
    },
    {
      "_class": "curvePoint",
      "cornerRadius": 0,
      "curveFrom": "{0.34756370083856319, 0.74832538993882225}",
      "curveMode": 4,
      "curveTo": "{0.38453698195871611, 0.969965090953402}",
      "hasCurveFrom": true,
      "hasCurveTo": false,
      "point": "{0.38453698195871611, 0.969965090953402}"
    },
    {
      "_class": "curvePoint",
      "cornerRadius": 0,
      "curveFrom": "{0.04900972049975276, 0.42730557523733742}",
      "curveMode": 4,
      "curveTo": "{0.22864150371247305, 0.53271755015680933}",
      "hasCurveFrom": true,
      "hasCurveTo": true,
      "point": "{0.059148040871999638, 0.43238065848128987}"
    },
    {
      "_class": "curvePoint",
      "cornerRadius": 0,
      "curveFrom": "{0.021843835348004936, 0.43396142211465194}",
      "curveMode": 4,
      "curveTo": "{0.038359971503386513, 0.42480963265834426}",
      "hasCurveFrom": true,
      "hasCurveTo": true,
      "point": "{0.030267365627616498, 0.42946872547246495}"
    },
    {
      "_class": "curvePoint",
      "cornerRadius": 0,
      "curveFrom": "{0.013239800848115759, 0.48758258852001862}",
      "curveMode": 3,
      "curveTo": "{0.016789717180237699, 0.44486037137625478}",
      "hasCurveFrom": true,
      "hasCurveTo": true,
      "point": "{0.015706691858573506, 0.45879605077563279}"
    },
    {
      "_class": "curvePoint",
      "cornerRadius": 0,
      "curveFrom": "{0.053191401602845606, 0.60555747442042174}",
      "curveMode": 3,
      "curveTo": "{0.023317953146936975, 0.51732590425301883}",
      "hasCurveFrom": true,
      "hasCurveTo": true,
      "point": "{0.033245685262193618, 0.54673642764215291}"
    },
    {
      "_class": "curvePoint",
      "cornerRadius": 0,
      "curveFrom": "{0.17169242221495506, 0.81317829794965724}",
      "curveMode": 3,
      "curveTo": "{0.07885308491894856, 0.66146658818986559}",
      "hasCurveFrom": true,
      "hasCurveTo": true,
      "point": "{0.10983964273323464, 0.71205102445745705}"
    },
    {
      "_class": "curvePoint",
      "cornerRadius": 0,
      "curveFrom": "{0.3570401724031263, 0.9471688153985991}",
      "curveMode": 4,
      "curveTo": "{0.25340066592718902, 0.89458762506781309}",
      "hasCurveFrom": true,
      "hasCurveTo": true,
      "point": "{0.34602941496620526, 0.94213533119763004}"
    },
    {
      "_class": "curvePoint",
      "cornerRadius": 0,
      "curveFrom": "{0.38977160434676056, 0.96114609384095995}",
      "curveMode": 4,
      "curveTo": "{0.36802084580333455, 0.95224389864255155}",
      "hasCurveFrom": true,
      "hasCurveTo": true,
      "point": "{0.37879093094655231, 0.95719418475755436}"
    },
    {
      "_class": "curvePoint",
      "cornerRadius": 0,
      "curveFrom": "{0.41086051408250279, 0.96880031774987174}",
      "curveMode": 4,
      "curveTo": "{0.40051160545326547, 0.9650564038813827}",
      "hasCurveFrom": false,
      "hasCurveTo": true,
      "point": "{0.41086051408250279, 0.96880031774987174}"
    },
    {
      "_class": "curvePoint",
      "cornerRadius": 0,
      "curveFrom": "{0.51266489431895323, 0.87973676672280465}",
      "curveMode": 4,
      "curveTo": "{0.40508437903362615, 0.97008988808235175}",
      "hasCurveFrom": true,
      "hasCurveTo": false,
      "point": "{0.40508437903362615, 0.97008988808235175}"
    },
    {
      "_class": "curvePoint",
      "cornerRadius": 0,
      "curveFrom": "{0.71428810836880285, 0.56304325249157439}",
      "curveMode": 4,
      "curveTo": "{0.60541397950482112, 0.7623026683811831}",
      "hasCurveFrom": true,
      "hasCurveTo": true,
      "point": "{0.67866860890073044, 0.62968491935068749}"
    },
    {
      "_class": "curvePoint",
      "cornerRadius": 0,
      "curveFrom": "{0.78221786326652887, 0.383709778190926}",
      "curveMode": 4,
      "curveTo": "{0.74912542288233996, 0.49365604879556829}",
      "hasCurveFrom": true,
      "hasCurveTo": true,
      "point": "{0.7717185344537274, 0.42044173314510636}"
    },
    {
      "_class": "curvePoint",
      "cornerRadius": 0,
      "curveFrom": "{0.77400492124390752, 0.27085157457745879}",
      "curveMode": 4,
      "curveTo": "{0.78733214950772168, 0.34414908831388696}",
      "hasCurveFrom": true,
      "hasCurveTo": true,
      "point": "{0.78038273702704219, 0.30737553431672321}"
    },
    {
      "_class": "curvePoint",
      "cornerRadius": 0,
      "curveFrom": "{0.70592474616261691, 0.21756320051595768}",
      "curveMode": 4,
      "curveTo": "{0.75604475132630689, 0.23811312774966681}",
      "hasCurveFrom": true,
      "hasCurveTo": true,
      "point": "{0.73095466470774895, 0.22800456030474531}"
    },
    {
      "_class": "curvePoint",
      "cornerRadius": 0,
      "curveFrom": "{0.63339213364781721, 0.26839723104144908}",
      "curveMode": 2,
      "curveTo": "{0.67755549954235317, 0.227754966046846}",
      "hasCurveFrom": true,
      "hasCurveTo": true,
      "point": "{0.65562423677864978, 0.24784730380773995}"
    },
    {
      "_class": "curvePoint",
      "cornerRadius": 0,
      "curveFrom": "{0.57554053104891223, 0.39743746237538752}",
      "curveMode": 4,
      "curveTo": "{0.61666540923544544, 0.29918052284902941}",
      "hasCurveFrom": true,
      "hasCurveTo": true,
      "point": "{0.60276658427408591, 0.33141978116102272}"
    },
    {
      "_class": "curvePoint",
      "cornerRadius": 0,
      "curveFrom": "{0.49566741357616539, 0.6728647259672671}",
      "curveMode": 3,
      "curveTo": "{0.55279699929396076, 0.46640867564156119}",
      "hasCurveFrom": true,
      "hasCurveTo": true,
      "point": "{0.53369363598126973, 0.53508869560685213}"
    },
    {
      "_class": "curvePoint",
      "cornerRadius": 0,
      "curveFrom": "{0.46401900695419557, 0.94666962688280043}",
      "curveMode": 4,
      "curveTo": "{0.47331497429848129, 0.8124295151759594}",
      "hasCurveFrom": false,
      "hasCurveTo": true,
      "point": "{0.46401900695419557, 0.94666962688280043}"
    },
    {
      "_class": "curvePoint",
      "cornerRadius": 0,
      "curveFrom": "{0.6318578477754595, 0.97874248902286076}",
      "curveMode": 4,
      "curveTo": "{0.45863396438258658, 0.9369770498677108}",
      "hasCurveFrom": true,
      "hasCurveTo": false,
      "point": "{0.45863396438258658, 0.9369770498677108}"
    },
    {
      "_class": "curvePoint",
      "cornerRadius": 0,
      "curveFrom": "{0.94509283803016442, 0.86862982224628538}",
      "curveMode": 3,
      "curveTo": "{0.7962671084114531, 0.94567124985120321}",
      "hasCurveFrom": true,
      "hasCurveTo": true,
      "point": "{0.9287271220583474, 0.87728242318679506}"
    },
    {
      "_class": "curvePoint",
      "cornerRadius": 0,
      "curveFrom": "{0.98426225383035926, 0.82798755725168283}",
      "curveMode": 4,
      "curveTo": "{0.96070645308415925, 0.85835485862943084}",
      "hasCurveFrom": true,
      "hasCurveTo": true,
      "point": "{0.97243922740218991, 0.8428800146396741}"
    },
    {
      "_class": "curvePoint",
      "cornerRadius": 0,
      "curveFrom": "{0.98961721236525524, 0.76446581861631058}",
      "curveMode": 4,
      "curveTo": "{0.9907604057603453, 0.80631445585742678}",
      "hasCurveFrom": true,
      "hasCurveTo": true,
      "point": "{0.990008304842523, 0.78547333532283492}"
    },
    {
      "_class": "curvePoint",
      "cornerRadius": 0,
      "curveFrom": "{0.95086897307904128, 0.73513849331314274}",
      "curveMode": 4,
      "curveTo": "{0.97923821969930502, 0.74745181003617467}",
      "hasCurveFrom": true,
      "hasCurveTo": true,
      "point": "{0.96500847033410386, 0.74150314688957464}"
    },
    {
      "_class": "curvePoint",
      "cornerRadius": 0,
      "curveFrom": "{0.85857114844386695, 0.73796722823600147}",
      "curveMode": 4,
      "curveTo": "{0.93516510591490776, 0.73559608278595801}",
      "hasCurveFrom": true,
      "hasCurveTo": true,
      "point": "{0.91988241526475523, 0.73634486555965595}"
    },
    {
      "_class": "curvePoint",
      "cornerRadius": 0,
      "curveFrom": "{0.65469163164054966, 0.80194655634418888}",
      "curveMode": 3,
      "curveTo": "{0.80270509226801345, 0.75057173825991608}",
      "hasCurveFrom": true,
      "hasCurveTo": true,
      "point": "{0.75345752416899758, 0.76754414779706859}"
    },
    {
      "_class": "curvePoint",
      "cornerRadius": 0,
      "curveFrom": "{0.51395850789760789, 0.91330719441026087}",
      "curveMode": 3,
      "curveTo": "{0.58327212848412746, 0.85456934571795828}",
      "hasCurveFrom": true,
      "hasCurveTo": true,
      "point": "{0.53715330020325314, 0.89367244612218211}"
    },
    {
      "_class": "curvePoint",
      "cornerRadius": 0,
      "curveFrom": "{0.47424757943658113, 0.95278468620133361}",
      "curveMode": 2,
      "curveTo": "{0.49693094311810698, 0.9299468116035472}",
      "hasCurveFrom": true,
      "hasCurveTo": true,
      "point": "{0.48558926127734414, 0.9413449493809487}"
    },
    {
      "_class": "curvePoint",
      "cornerRadius": 0,
      "curveFrom": "{0.4680803519104369, 0.95815096274616818}",
      "curveMode": 4,
      "curveTo": "{0.4680803519104369, 0.95815096274616818}",
      "hasCurveFrom": false,
      "hasCurveTo": true,
      "point": "{0.4680803519104369, 0.95815096274616818}"
    }
  ],
  "resizingConstraint": 63,
  "resizingType": 0,
  "rotation": 0,
  "shouldBreakMaskChain": false,
  "style": {
    "_class": "style",
    "blur": {
      "_class": "blur",
      "center": "{0.5, 0.5}",
      "isEnabled": false,
      "motionAngle": 0,
      "radius": 5.999999642372131,
      "saturation": 1,
      "type": 0
    },
    "borderOptions": {
      "_class": "borderOptions",
      "dashPattern": [
      ],
      "isEnabled": true,
      "lineCapStyle": 0,
      "lineJoinStyle": 0
    },
    "borders": [
    ],
    "colorControls": {
      "_class": "colorControls",
      "brightness": 0,
      "contrast": 1,
      "hue": 0,
      "isEnabled": false,
      "saturation": 1
    },
    "contextSettings": {
      "_class": "graphicsContextSettings",
      "blendMode": 0,
      "opacity": 1
    },
    "do_objectID": "73AD017C-ABC6-4F1F-B49F-5D52BB6C1F98",
    "endMarkerType": 0,
    "fills": [
      {
        "_class": "fill",
        "color": {
          "_class": "color",
          "alpha": 1,
          "blue": 0.1612028479576111,
          "green": 0.1451762616634369,
          "red": 0.07425963133573532
        },
        "contextSettings": {
          "_class": "graphicsContextSettings",
          "blendMode": 0,
          "opacity": 1
        },
        "fillType": 0,
        "gradient": {
          "_class": "gradient",
          "elipseLength": 0,
          "from": "{0.5, 0}",
          "gradientType": 0,
          "stops": [
            {
              "_class": "gradientStop",
              "color": {
                "_class": "color",
                "alpha": 1,
                "blue": 1,
                "green": 1,
                "red": 1
              },
              "position": 0
            },
            {
              "_class": "gradientStop",
              "color": {
                "_class": "color",
                "alpha": 1,
                "blue": 0,
                "green": 0,
                "red": 0
              },
              "position": 1
            }
          ],
          "to": "{0.5, 1}"
        },
        "isEnabled": true,
        "noiseIndex": 0,
        "noiseIntensity": 0,
        "patternFillType": 1,
        "patternTileScale": 1
      }
    ],
    "innerShadows": [
    ],
    "miterLimit": 10,
    "shadows": [
    ],
    "startMarkerType": 0,
    "windingRule": 1
  }
}