{
  "_class": "shapePath",
  "booleanOperation": -1,
  "clippingMaskMode": 0,
  "do_objectID": "A577ADAC-C80D-4A0E-BACA-C47F4DEA7A5D",
  "edited": true,
  "exportOptions": {
    "_class": "exportOptions",
    "exportFormats": [
    ],
    "includedLayerIds": [
    ],
    "layerOptions": 0,
    "shouldTrim": false
  },
  "frame": {
    "_class": "rect",
    "constrainProportions": false,
    "height": 3.936800225471826,
    "width": 3.253448151917783,
    "x": 41.31376684163492,
    "y": 95.09885742294449
  },
  "hasClippingMask": false,
  "isClosed": false,
  "isFixedToViewport": false,
  "isFlippedHorizontal": false,
  "isFlippedVertical": false,
  "isLocked": false,
  "isVisible": true,
  "layerListExpandedType": 0,
  "name": "Fill 196",
  "nameIsFixed": false,
  "pointRadiusBehaviour": 1,
  "points": [
    {
      "_class": "curvePoint",
      "cornerRadius": 0,
      "curveFrom": "{0.54088027099807856, -0.0036709699847791684}",
      "curveMode": 4,
      "curveTo": "{0.85525555211359161, 8.9377654810533942e-05}",
      "hasCurveFrom": true,
      "hasCurveTo": false,
      "point": "{0.85525555211359161, 8.9377654810533942e-05}"
    },
    {
      "_class": "curvePoint",
      "cornerRadius": 0,
      "curveFrom": "{-0.031613661980699433, 0.49508786693885709}",
      "curveMode": 2,
      "curveTo": "{0.25939029889399079, 0.11144694525444988}",
      "hasCurveFrom": true,
      "hasCurveTo": true,
      "point": "{0.11388831845664495, 0.30331013731983081}"
    },
    {
      "_class": "curvePoint",
      "cornerRadius": 0,
      "curveFrom": "{0.3987909169675804, 0.9754722778963183}",
      "curveMode": 4,
      "curveTo": "{-0.038128676030133021, 0.75959413840538381}",
      "hasCurveFrom": true,
      "hasCurveTo": true,
      "point": "{0.096825186422415568, 1}"
    },
    {
      "_class": "curvePoint",
      "cornerRadius": 0,
      "curveFrom": "{0.98286709714535048, 0.4973098905440671}",
      "curveMode": 2,
      "curveTo": "{0.66249386658750276, 0.85847418883729565}",
      "hasCurveFrom": true,
      "hasCurveTo": true,
      "point": "{0.82268048186642517, 0.67789203969068135}"
    },
    {
      "_class": "curvePoint",
      "cornerRadius": 0,
      "curveFrom": "{0.97407699882468557, 0.010857645895451455}",
      "curveMode": 4,
      "curveTo": "{1.0377793584191464, 0.25485293023694788}",
      "hasCurveFrom": false,
      "hasCurveTo": true,
      "point": "{0.97407699882468557, 0.010857645895451455}"
    }
  ],
  "resizingConstraint": 63,
  "resizingType": 0,
  "rotation": 0,
  "shouldBreakMaskChain": false,
  "style": {
    "_class": "style",
    "blur": {
      "_class": "blur",
      "center": "{0.5, 0.5}",
      "isEnabled": false,
      "motionAngle": 0,
      "radius": 5.999999642372131,
      "saturation": 1,
      "type": 0
    },
    "borderOptions": {
      "_class": "borderOptions",
      "dashPattern": [
      ],
      "isEnabled": true,
      "lineCapStyle": 0,
      "lineJoinStyle": 0
    },
    "borders": [
    ],
    "colorControls": {
      "_class": "colorControls",
      "brightness": 0,
      "contrast": 1,
      "hue": 0,
      "isEnabled": false,
      "saturation": 1
    },
    "contextSettings": {
      "_class": "graphicsContextSettings",
      "blendMode": 0,
      "opacity": 1
    },
    "do_objectID": "BF28F858-C851-49A5-B9E5-B07C1EDCD5EA",
    "endMarkerType": 0,
    "fills": [
      {
        "_class": "fill",
        "color": {
          "_class": "color",
          "alpha": 1,
          "blue": 0.371923565864563,
          "green": 0.335692822933197,
          "red": 0.8775075078010559
        },
        "contextSettings": {
          "_class": "graphicsContextSettings",
          "blendMode": 0,
          "opacity": 1
        },
        "fillType": 0,
        "gradient": {
          "_class": "gradient",
          "elipseLength": 0,
          "from": "{0.5, 0}",
          "gradientType": 0,
          "stops": [
            {
              "_class": "gradientStop",
              "color": {
                "_class": "color",
                "alpha": 1,
                "blue": 1,
                "green": 1,
                "red": 1
              },
              "position": 0
            },
            {
              "_class": "gradientStop",
              "color": {
                "_class": "color",
                "alpha": 1,
                "blue": 0,
                "green": 0,
                "red": 0
              },
              "position": 1
            }
          ],
          "to": "{0.5, 1}"
        },
        "isEnabled": true,
        "noiseIndex": 0,
        "noiseIntensity": 0,
        "patternFillType": 1,
        "patternTileScale": 1
      }
    ],
    "innerShadows": [
    ],
    "miterLimit": 10,
    "shadows": [
    ],
    "startMarkerType": 0,
    "windingRule": 1
  }
}